zope/app/session/__init__.py
zope/app/session/api.rst
zope/app/session/browser.zcml
zope/app/session/configure.zcml
zope/app/session/ftesting.zcml
zope/app/session/http.py
zope/app/session/interfaces.py
zope/app/session/session.py
zope/app/session/testing.py
zope/app/session/tests.py
zope_app_session-6.0.dist-info/METADATA
zope_app_session-6.0.dist-info/WHEEL
zope_app_session-6.0.dist-info/top_level.txt
zope_app_session-6.0.dist-info/RECORD
