Metadata-Version: 2.4
Name: zope.app.session
Version: 6.0
Summary: Zope session
Home-page: https://github.com/zopefoundation/zope.app.session
Author: Zope Foundation and Contributors
Author-email: zope-dev@zope.dev
License: ZPL-2.1
Keywords: zope3 session
Classifier: Development Status :: 5 - Production/Stable
Classifier: Environment :: Web Environment
Classifier: Intended Audience :: Developers
Classifier: License :: OSI Approved :: Zope Public License
Classifier: Programming Language :: Python
Classifier: Programming Language :: Python :: 3
Classifier: Programming Language :: Python :: 3.9
Classifier: Programming Language :: Python :: 3.10
Classifier: Programming Language :: Python :: 3.11
Classifier: Programming Language :: Python :: 3.12
Classifier: Programming Language :: Python :: 3.13
Classifier: Programming Language :: Python :: Implementation :: CPython
Classifier: Programming Language :: Python :: Implementation :: PyPy
Classifier: Natural Language :: English
Classifier: Operating System :: OS Independent
Classifier: Topic :: Internet :: WWW/HTTP
Classifier: Framework :: Zope :: 3
Requires-Python: >=3.9
Requires-Dist: setuptools
Requires-Dist: zope.session
Provides-Extra: test
Requires-Dist: transaction; extra == "test"
Requires-Dist: webtest; extra == "test"
Requires-Dist: zope.app.basicskin>=4.0.0; extra == "test"
Requires-Dist: zope.app.form>=5.0.0; extra == "test"
Requires-Dist: zope.app.appsetup>=4.0.0; extra == "test"
Requires-Dist: zope.app.component>=4.0.0; extra == "test"
Requires-Dist: zope.app.container>=4.0.0; extra == "test"
Requires-Dist: zope.app.publication>=4.2.1; extra == "test"
Requires-Dist: zope.app.rotterdam>=4.0.1; extra == "test"
Requires-Dist: zope.app.securitypolicy; extra == "test"
Requires-Dist: zope.app.wsgi; extra == "test"
Requires-Dist: zope.container; extra == "test"
Requires-Dist: zope.pagetemplate; extra == "test"
Requires-Dist: zope.site; extra == "test"
Requires-Dist: zope.testbrowser; extra == "test"
Requires-Dist: zope.testing; extra == "test"
Requires-Dist: zope.testrunner>=6.4; extra == "test"
Dynamic: author
Dynamic: author-email
Dynamic: classifier
Dynamic: description
Dynamic: home-page
Dynamic: keywords
Dynamic: license
Dynamic: provides-extra
Dynamic: requires-dist
Dynamic: requires-python
Dynamic: summary
